setup.py
distributions/Binomialdistribution.py
distributions/Gaussiandistribution.py
distributions/Generaldistribution.py
distributions/__init__.py
distributions8989.egg-info/PKG-INFO
distributions8989.egg-info/SOURCES.txt
distributions8989.egg-info/dependency_links.txt
distributions8989.egg-info/not-zip-safe
distributions8989.egg-info/top_level.txt